LICENSE.txt
MANIFEST.in
README.rst
setup.py
geohash/__init__.py
geohash/geohash.py
geohash2.egg-info/PKG-INFO
geohash2.egg-info/SOURCES.txt
geohash2.egg-info/dependency_links.txt
geohash2.egg-info/requires.txt
geohash2.egg-info/top_level.txt