Metadata-Version: 1.0
Name: geohash2
Version: 1.0
Summary: (Geohash fixed for python3) Module to decode/encode Geohashes to/from latitude and longitude.  See http://en.wikipedia.org/wiki/Geohash
Home-page: https://github.com/dbarthe/geohash/
Author: Leonard Norrgard, Barthelemy Delemotte
Author-email: barthelemy.delemotte@gmail.com
License: GNU Affero General Public License as published by the Free Software Foundation, either version 3 of the License, or (at your option) any later version.
Keywords: Geohash GIS latitude longitude encode decode Galileo GPS WGS84 coordinates geotagging
Platform: UNKNOWN
